tinyobjloader.cpython-37m-i386-linux-gnu.so
tinymetabobjloader-0.1.1.dist-info/RECORD
tinymetabobjloader-0.1.1.dist-info/METADATA
tinymetabobjloader-0.1.1.dist-info/top_level.txt
tinymetabobjloader-0.1.1.dist-info/WHEEL
tinymetabobjloader-0.1.1.dist-info/LICENSE
