Metadata-Version: 2.1
Name: tinymetabobjloader
Version: 0.1.1
Summary: Experimental fork of tinyobjloader Python module
Home-page: https://github.com/metabolize/tinyobjloader
Author: Syoyo Fujita, Paul Melnikow
Author-email: syoyo@lighttransport.com, github@paulmelnikow.com
License: UNKNOWN
Platform: UNKNOWN
Classifier: License :: OSI Approved :: MIT License
